{
  "zone2": [
  {
    "id": 1,
    "Nomdusite": "Boudjounkoura",
    "Capacité": 81,
    "Région": "Adamaoua",
    "Département": "Mayo-Banyo",
    "Arrondissement": "Banyo",
    "Zone": "Zone 2",
    "Phase": "Phase 2",
    "Responsible": ""
  },
  {
    "id": 2,
    "Nomdusite": "Kouroum",
    "Capacité": 54,
    "Région": "Adamaoua",
    "Département": "Mayo-Banyo",
    "Arrondissement": "Bankim",
    "Zone": "Zone 2",
    "Phase": "Phase 2",
    "Responsible": ""
  },
  {
    "id": 3,
    "Nomdusite": "Mayo-Darle II",
    "Capacité": 140.4,
    "Région": "Adamaoua",
    "Département": "Mayo-Banyo",
    "Arrondissement": "Mayo-Darle",
    "Zone": "Zone 2",
    "Phase": "Phase 2",
    "Responsible": ""
  },
  {
    "id": 4,
    "Nomdusite": "Mayo-Djinga",
    "Capacité": 81,
    "Région": "Adamaoua",
    "Département": "Mayo-Banyo",
    "Arrondissement": "Mayo-Darle",
    "Zone": "Zone 2",
    "Phase": "Phase 2",
    "Responsible": ""
  },
  {
    "id": 5,
    "Nomdusite": "Mayo-KeleleLess",
    "Capacité": 32.4,
    "Région": "Adamaoua",
    "Département": "Mayo-Banyo",
    "Arrondissement": "Banyo",
    "Zone": "Zone 2",
    "Phase": "Phase 2",
    "Responsible": ""
  },
  {
    "id": 6,
    "Nomdusite": "Tchamba",
    "Capacité": 97.2,
    "Région": "Adamaoua",
    "Département": "Mayo-Banyo",
    "Arrondissement": "Bankim",
    "Zone": "Zone 2",
    "Phase": "Phase 2",
    "Responsible": ""
  },
  {
    "id": 7,
    "Nomdusite": "Nditem",
    "Capacité": 54,
    "Région": "Adamaoua",
    "Département": "Mayo-Banyo",
    "Arrondissement": "Bankim",
    "Zone": "Zone 2",
    "Phase": "Phase 2",
    "Responsible": ""
  },
  {
    "id": 8,
    "Nomdusite": "Ouamayari",
    "Capacité": 54,
    "Région": "Adamaoua",
    "Département": "Mayo-Banyo",
    "Arrondissement": "Banyo",
    "Zone": "Zone 2",
    "Phase": "Phase 2",
    "Responsible": ""
  },
  {
    "id": 9,
    "Nomdusite": "Atta",
    "Capacité": 80,
    "Région": "Adamaoua",
    "Département": "Mayo-Banyo",
    "Arrondissement": "Mayo-Banyo",
    "Zone": "Zone 2",
    "Phase": "Phase 1",
    "Responsible": ""
  },
  {
    "id": 10,
    "Nomdusite": "Lingam",
    "Capacité": 80,
    "Région": "Adamaoua",
    "Département": "Mayo-Banyo",
    "Arrondissement": "Mayo-Banyo",
    "Zone": "Zone 2",
    "Phase": "Phase 1",
    "Responsible": ""
  },
  {
    "id": 11,
    "Nomdusite": "Somie",
    "Capacité": 100,
    "Région": "Adamaoua",
    "Département": "Mayo-Banyo",
    "Arrondissement": "Mayo-Banyo",
    "Zone": "Zone 2",
    "Phase": "Phase 1",
    "Responsible": ""
  },
  {
    "id": 12,
    "Nomdusite": "Mbamti-Djoumbare",
    "Capacité": 80,
    "Région": "Adamaoua",
    "Département": "Mayo-Banyo",
    "Arrondissement": "Banyo",
    "Zone": "Zone 2",
    "Phase": "Phase 1",
    "Responsible": ""
  },
  {
    "id": 13,
    "Nomdusite": "Songkolong",
    "Capacité": 80,
    "Région": "Adamaoua",
    "Département": "Mayo-Banyo",
    "Arrondissement": "Mayo-Banyo",
    "Zone": "Zone 2",
    "Phase": "Phase 1",
    "Responsible": ""
  },
  {
    "id": 14,
    "Nomdusite": "Tong",
    "Capacité": 100,
    "Région": "Adamaoua",
    "Département": "Mayo-Banyo",
    "Arrondissement": "Mayo-Banyo",
    "Zone": "Zone 2",
    "Phase": "Phase 1",
    "Responsible": ""
  },
  {
    "id": 15,
    "Nomdusite": "Sambo-Labo",
    "Capacité": 80,
    "Région": "Adamaoua",
    "Département": "Manyo-Banyo",
    "Arrondissement": "Manyo-Banyo",
    "Zone": "Zone 2",
    "Phase": "Phase 1",
    "Responsible": ""
  },
  {
    "id": 16,
    "Nomdusite": "Allat",
    "Capacité": 80,
    "Région": "Adamaoua",
    "Département": "Manyo-Banyo",
    "Arrondissement": "Manyo-Banyo",
    "Zone": "Zone 2",
    "Phase": "Phase 1",
    "Responsible": ""
  },
  {
    "id": 17,
    "Nomdusite": "Mayo Darle",
    "Capacité": 80,
    "Région": "Adamaoua",
    "Département": "Manyo-Banyo",
    "Arrondissement": "Manyo-Banyo",
    "Zone": "Zone 2",
    "Phase": "Phase 1",
    "Responsible": ""
  },
  {
    "id": 18,
    "Nomdusite": "Ribao",
    "Capacité": 80,
    "Région": "Adamaoua",
    "Département": "Mayo-Banyo",
    "Arrondissement": "Mayo-Darle",
    "Zone": "Zone 2",
    "Phase": "Phase 1",
    "Responsible": ""
  },
  {
    "id": 19,
    "Nomdusite": "Bakem",
    "Capacité": 80,
    "Région": "Sud-ouest",
    "Département": "Manyu",
    "Arrondissement": "Akwaya",
    "Zone": "Zone 2",
    "Phase": "Phase 1",
    "Responsible": ""
  },
  {
    "id": 20,
    "Nomdusite": "Okpambe",
    "Capacité": 80,
    "Région": "Sud-ouest",
    "Département": "Manyu",
    "Arrondissement": "Akwaya",
    "Zone": "Zone 2",
    "Phase": "Phase 1",
    "Responsible": ""
  },
  {
    "id": 21,
    "Nomdusite": "Nzalla",
    "Capacité": 50,
    "Région": "Ouest",
    "Département": "Menoua",
    "Arrondissement": "Fokoue",
    "Zone": "Zone 2",
    "Phase": "Phase 1",
    "Responsible": ""
  },
  {
    "id": 22,
    "Nomdusite": "Menfoung",
    "Capacité": 50,
    "Région": "Ouest",
    "Département": "Bamboutos",
    "Arrondissement": "Galim",
    "Zone": "Zone 2",
    "Phase": "Phase 1",
    "Responsible": ""
  },
  {
    "id": 23,
    "Nomdusite": "Makpa",
    "Capacité": 50,
    "Région": "Ouest",
    "Département": "Noun",
    "Arrondissement": "Malantouen",
    "Zone": "Zone 2",
    "Phase": "Phase 1",
    "Responsible": ""
  },
  {
    "id": 24,
    "Nomdusite": "Mantchoutbi",
    "Capacité": 100,
    "Région": "Ouest",
    "Département": "Noun ",
    "Arrondissement": "Messangam",
    "Zone": "Zone 2",
    "Phase": "Phase 1",
    "Responsible": ""
  },
  {
    "id": 25,
    "Nomdusite": "Makoup",
    "Capacité": 80,
    "Région": "Ouest",
    "Département": "Noun",
    "Arrondissement": "Malantouen",
    "Zone": "Zone 2",
    "Phase": "Phase 1",
    "Responsible": ""
  },
  {
    "id": 26,
    "Nomdusite": "Machatoum",
    "Capacité": 100,
    "Région": "Ouest",
    "Département": "Noun ",
    "Arrondissement": "Massangam",
    "Zone": "Zone 2",
    "Phase": "Phase 1",
    "Responsible": ""
  },
  {
    "id": 27,
    "Nomdusite": "Mankouombi",
    "Capacité": 100,
    "Région": "Ouest",
    "Département": "Noun",
    "Arrondissement": "Massangam",
    "Zone": "Zone 2",
    "Phase": "Phase 1",
    "Responsible": ""
  },
  {
    "id": 28,
    "Nomdusite": "Njissain",
    "Capacité": 30,
    "Région": "Ouest",
    "Département": "Noun",
    "Arrondissement": "Malantouen",
    "Zone": "Zone 2",
    "Phase": "Phase 1",
    "Responsible": ""
  },
  {
    "id": 29,
    "Nomdusite": "Bekambe",
    "Capacité": 80,
    "Région": "Ouest",
    "Département": "Haut Nkam",
    "Arrondissement": "Bakou",
    "Zone": "Zone 2",
    "Phase": "Phase 1",
    "Responsible": ""
  },
  {
    "id": 30,
    "Nomdusite": "Bagnoun",
    "Capacité": 80,
    "Région": "Ouest",
    "Département": "Nde",
    "Arrondissement": "Bazou",
    "Zone": "Zone 2",
    "Phase": "Phase 1",
    "Responsible": ""
  },
  {
    "id": 31,
    "Nomdusite": "Mangourain(Nkouombi)",
    "Capacité": 54,
    "Région": "Ouest",
    "Département": "Noun",
    "Arrondissement": "Massangam",
    "Zone": "Zone 2",
    "Phase": "Phase 2",
    "Responsible": ""
  },
  {
    "id": 32,
    "Nomdusite": "Batoula-Bamenghui",
    "Capacité": 54,
    "Région": "Ouest",
    "Département": "Bamboutos",
    "Arrondissement": "Batcham",
    "Zone": "Zone 2",
    "Phase": "Phase 2",
    "Responsible": ""
  },
  {
    "id": 33,
    "Nomdusite": "Bamboue 2",
    "Capacité": 54,
    "Région": "Ouest",
    "Département": "Batcham",
    "Arrondissement": "Bamboutous",
    "Zone": "Zone 2",
    "Phase": "Phase 2",
    "Responsible": ""
  },
  {
    "id": 34,
    "Nomdusite": "Makoutam-Plateau",
    "Capacité": 54,
    "Région": "Ouest",
    "Département": "Noun",
    "Arrondissement": "Malentouen",
    "Zone": "Zone 2",
    "Phase": "Phase 2",
    "Responsible": ""
  },
  {
    "id": 35,
    "Nomdusite": "Njigbachouh",
    "Capacité": 54,
    "Région": "Ouest",
    "Département": "Noun",
    "Arrondissement": "Malentouen",
    "Zone": "Zone 2",
    "Phase": "Phase 2",
    "Responsible": ""
  },
  {
    "id": 36,
    "Nomdusite": "Fotemo",
    "Capacité": 54,
    "Région": "Ouest",
    "Département": "Menoua",
    "Arrondissement": "Penka-Michel",
    "Zone": "Zone 2",
    "Phase": "Phase 2",
    "Responsible": ""
  },
  {
    "id": 37,
    "Nomdusite": "Mankang-Mayong",
    "Capacité": 54,
    "Région": "Ouest",
    "Département": "Menoua",
    "Arrondissement": "Santchou",
    "Zone": "Zone 2",
    "Phase": "Phase 2",
    "Responsible": ""
  },
  {
    "id": 38,
    "Nomdusite": "Baboutcheu-Ngaleu",
    "Capacité": 21.6,
    "Région": "Ouest",
    "Département": "Haut-Nkam",
    "Arrondissement": "Bafang",
    "Zone": "Zone 2",
    "Phase": "Phase 2",
    "Responsible": ""
  },
  {
    "id": 39,
    "Nomdusite": "Mbakop",
    "Capacité": 54,
    "Région": "Ouest",
    "Département": "Noun",
    "Arrondissement": "Magba",
    "Zone": "Zone 2",
    "Phase": "Phase 2",
    "Responsible": ""
  },
  {
    "id": 40,
    "Nomdusite": "Tsah-Bamendou",
    "Capacité": 54,
    "Région": "Ouest",
    "Département": "Menoua",
    "Arrondissement": "Penka Michel",
    "Zone": "Zone 2",
    "Phase": "Phase 2",
    "Responsible": ""
  },
  {
    "id": 41,
    "Nomdusite": "Mayoh(Njitoukwet)",
    "Capacité": 81,
    "Région": "Ouest",
    "Département": "Noun",
    "Arrondissement": "Njimom",
    "Zone": "Zone 2",
    "Phase": "Phase 2",
    "Responsible": ""
  },
  {
    "id": 42,
    "Nomdusite": "Makpa I",
    "Capacité": 97.2,
    "Région": "Ouest",
    "Département": "Noun",
    "Arrondissement": "Malentouen",
    "Zone": "Zone 2",
    "Phase": "Phase 2",
    "Responsible": ""
  },
  {
    "id": 43,
    "Nomdusite": "Mamegnam-Njitoum",
    "Capacité": 140.4,
    "Région": "Ouest",
    "Département": "Noun",
    "Arrondissement": "Massangam",
    "Zone": "Zone 2",
    "Phase": "Phase 2",
    "Responsible": ""
  },
  {
    "id": 44,
    "Nomdusite": "Mankoutmbou 1",
    "Capacité": 140.4,
    "Région": "Ouest",
    "Département": "Noun",
    "Arrondissement": "Malantouen",
    "Zone": "Zone 2",
    "Phase": "Phase 2",
    "Responsible": ""
  },
  {
    "id": 45,
    "Nomdusite": "Njinga-Ndoutain",
    "Capacité": 97.2,
    "Région": "Ouest",
    "Département": "Noun",
    "Arrondissement": "Malentouen",
    "Zone": "Zone 2",
    "Phase": "Phase 2",
    "Responsible": ""
  },
  {
    "id": 46,
    "Nomdusite": "Belekwet Chefferie",
    "Capacité": 21.6,
    "Région": "Ouest",
    "Département": "Menoua",
    "Arrondissement": "Baleveng",
    "Zone": "Zone 2",
    "Phase": "Phase 2",
    "Responsible": ""
  },
  {
    "id": 47,
    "Nomdusite": "Bamela",
    "Capacité": 32.4,
    "Région": "Ouest",
    "Département": "Bamboutos",
    "Arrondissement": "Babadjou",
    "Zone": "Zone 2",
    "Phase": "Phase 2",
    "Responsible": ""
  },
  {
    "id": 48,
    "Nomdusite": "Fondjomekwet",
    "Capacité": 81,
    "Région": "Ouest",
    "Département": "Haut Nkam",
    "Arrondissement": "Bandja",
    "Zone": "Zone 2",
    "Phase": "Phase 2",
    "Responsible": ""
  },
  {
    "id": 49,
    "Nomdusite": "Feuguimbou(Nfenguembou)",
    "Capacité": 183.6,
    "Région": "Ouest",
    "Département": "Noun",
    "Arrondissement": "Malentouen",
    "Zone": "Zone 2",
    "Phase": "Phase 2",
    "Responsible": ""
  },
  {
    "id": 50,
    "Nomdusite": "Babessi",
    "Capacité": 30,
    "Région": "Nord-Ouest",
    "Département": "Ngokentunja",
    "Arrondissement": "Babessi",
    "Zone": "Zone 2",
    "Phase": "Phase 1",
    "Responsible": ""
  },
  {
    "id": 51,
    "Nomdusite": "Bamessing(Ndop)",
    "Capacité": 15,
    "Région": "Nord-Ouest",
    "Département": "Ngoketunjia",
    "Arrondissement": "Ndop",
    "Zone": "Zone 2",
    "Phase": "Phase 1",
    "Responsible": ""
  },
  {
    "id": 52,
    "Nomdusite": "Fonfuka",
    "Capacité": 80,
    "Région": "Nord-Ouest",
    "Département": "Boyo",
    "Arrondissement": "Bum",
    "Zone": "Zone 2",
    "Phase": "Phase 1",
    "Responsible": ""
  },
  {
    "id": 53,
    "Nomdusite": "Kandji-Chunghe",
    "Capacité": 50,
    "Région": "Nord-Ouest",
    "Département": "Donga-Mantung",
    "Arrondissement": "Misaje",
    "Zone": "Zone 2",
    "Phase": "Phase 1",
    "Responsible": ""
  },
  {
    "id": 54,
    "Nomdusite": "Akweto",
    "Capacité": 15,
    "Région": "Nord-Ouest",
    "Département": "Donga Mantug",
    "Arrondissement": "Misaje",
    "Zone": "Zone 2",
    "Phase": "Phase 1",
    "Responsible": ""
  },
  {
    "id": 55,
    "Nomdusite": "NJAP",
    "Capacité": 80,
    "Région": "Nord-Ouest",
    "Département": "Donga-Mantung",
    "Arrondissement": "Nkambe",
    "Zone": "Zone 2",
    "Phase": "Phase 1",
    "Responsible": ""
  },
  {
    "id": 56,
    "Nomdusite": "Bua Bua",
    "Capacité": 100,
    "Région": "Nord-Ouest",
    "Département": "Boyo ",
    "Arrondissement": "Fonfuka ",
    "Zone": "Zone 2",
    "Phase": "Phase 1",
    "Responsible": ""
  },
  {
    "id": 57,
    "Nomdusite": "Andek",
    "Capacité": 80,
    "Région": "Nord-Ouest",
    "Département": "Momo",
    "Arrondissement": "Ngie",
    "Zone": "Zone 2",
    "Phase": "Phase 1",
    "Responsible": ""
  },
  {
    "id": 58,
    "Nomdusite": "Bonanyamg",
    "Capacité": 80,
    "Région": "Nord-Ouest",
    "Département": "Momo",
    "Arrondissement": "Andek",
    "Zone": "Zone 2",
    "Phase": "Phase 1",
    "Responsible": ""
  },
  {
    "id": 59,
    "Nomdusite": "Kugwe",
    "Capacité": 80,
    "Région": "Nord-Ouest",
    "Département": "Momo",
    "Arrondissement": "Batibo",
    "Zone": "Zone 2",
    "Phase": "Phase 1",
    "Responsible": ""
  },
  {
    "id": 60,
    "Nomdusite": "Njikwa",
    "Capacité": 80,
    "Région": "Nord-Ouest",
    "Département": "Momo",
    "Arrondissement": "Njikwa",
    "Zone": "Zone 2",
    "Phase": "Phase 1",
    "Responsible": ""
  },
  {
    "id": 61,
    "Nomdusite": "Teze",
    "Capacité": 100,
    "Région": "Nord-Ouest",
    "Département": "Momo",
    "Arrondissement": "Ngie",
    "Zone": "Zone 2",
    "Phase": "Phase 1",
    "Responsible": ""
  },
  {
    "id": 62,
    "Nomdusite": "Baba 1",
    "Capacité": 80,
    "Région": "Nord-Ouest",
    "Département": "Ngokentunja",
    "Arrondissement": "Ndop",
    "Zone": "Zone 2",
    "Phase": "Phase 1",
    "Responsible": ""
  },
  {
    "id": 63,
    "Nomdusite": "Nyebai Oshie",
    "Capacité": 100,
    "Région": "Nord-Ouest",
    "Département": "Momo",
    "Arrondissement": "Ngir",
    "Zone": "Zone 2",
    "Phase": "Phase 1",
    "Responsible": ""
  },
  {
    "id": 64,
    "Nomdusite": "Tinekoh-Ngie",
    "Capacité": 80,
    "Région": "Nord-Ouest",
    "Département": "Momo",
    "Arrondissement": "Andek",
    "Zone": "Zone 2",
    "Phase": "Phase 1",
    "Responsible": ""
  },
  {
    "id": 65,
    "Nomdusite": "Bessi",
    "Capacité": 80,
    "Région": "Nord-Ouest",
    "Département": "MOMO",
    "Arrondissement": "Batibo",
    "Zone": "Zone 2",
    "Phase": "Phase 1",
    "Responsible": ""
  },
  {
    "id": 66,
    "Nomdusite": "Mbanje-Njap",
    "Capacité": 15,
    "Région": "Nord-Ouest",
    "Département": "Donga-Mantung",
    "Arrondissement": "Nkambe",
    "Zone": "Zone 2",
    "Phase": "Phase 1",
    "Responsible": ""
  },
  {
    "id": 67,
    "Nomdusite": "Akwenko",
    "Capacité": 32.4,
    "Région": "Nord-Ouest",
    "Département": "Donga Mantung",
    "Arrondissement": "Ako",
    "Zone": "Zone 2",
    "Phase": "Phase 2",
    "Responsible": ""
  },
  {
    "id": 68,
    "Nomdusite": "Bessi-Fomukong",
    "Capacité": 32.4,
    "Région": "Nord-Ouest",
    "Département": "Momo",
    "Arrondissement": "Mbengwi",
    "Zone": "Zone 2",
    "Phase": "Phase 2",
    "Responsible": ""
  },
  {
    "id": 69,
    "Nomdusite": "Fringyen",
    "Capacité": 32.4,
    "Région": "Nord-Ouest",
    "Département": "Momo",
    "Arrondissement": "Mbengwi",
    "Zone": "Zone 2",
    "Phase": "Phase 2",
    "Responsible": ""
  }
]
}